MANIFEST.in
README.rst
setup.py
docs/HISTORY.txt
docs/LICENSE.GPL
docs/LICENSE.txt
docs/anthrazit_moPage_xml_import_v12.pdf
ftw/__init__.py
ftw.mopage.egg-info/PKG-INFO
ftw.mopage.egg-info/SOURCES.txt
ftw.mopage.egg-info/dependency_links.txt
ftw.mopage.egg-info/entry_points.txt
ftw.mopage.egg-info/namespace_packages.txt
ftw.mopage.egg-info/not-zip-safe
ftw.mopage.egg-info/requires.txt
ftw.mopage.egg-info/top_level.txt
ftw/mopage/__init__.py
ftw/mopage/configure.zcml
ftw/mopage/data_provider.py
ftw/mopage/data_validator.py
ftw/mopage/helpers.py
ftw/mopage/interfaces.py
ftw/mopage/object_lookup.py
ftw/mopage/testing.py
ftw/mopage/xml_generator.py
ftw/mopage/browser/__init__.py
ftw/mopage/browser/base.py
ftw/mopage/browser/configure.zcml
ftw/mopage/browser/events.py
ftw/mopage/browser/geolocations.py
ftw/mopage/browser/news.py
ftw/mopage/profiles/default/metadata.xml
ftw/mopage/profiles/default/propertiestool.xml
ftw/mopage/tests/__init__.py
ftw/mopage/tests/events.dtd
ftw/mopage/tests/geolocations.dtd
ftw/mopage/tests/news.dtd
ftw/mopage/tests/test.zcml
ftw/mopage/tests/test_components.py
ftw/mopage/tests/test_helpers.py
ftw/mopage/tests/test_setup.py
ftw/mopage/tests/test_validator.py
ftw/mopage/tests/test_views.py
ftw/mopage/tests/test_xml_writer.py