Metadata-Version: 1.1
Name: ftw.mopage
Version: 1.0
Summary: Provides moPage integration for Plone.
Home-page: https://github.com/4teamwork/ftw.mopage
Author: 4teamwork AG
Author-email: mailto:info@4teamwork.ch
License: GPL2
Platform: UNKNOWN
Classifier: Framework :: Plone
Classifier: Framework :: Plone :: 4.1
Classifier: Framework :: Plone :: 4.2
Classifier: Programming Language :: Python
Classifier: Topic :: Software Development :: Libraries :: Python Modules
